simplesum/__init__.py
simplesum/simplesum.py
simple_sum-0.0.7.dist-info/LICENSE
simple_sum-0.0.7.dist-info/METADATA
simple_sum-0.0.7.dist-info/WHEEL
simple_sum-0.0.7.dist-info/top_level.txt
simple_sum-0.0.7.dist-info/RECORD
