Metadata-Version: 2.1
Name: simple-sum
Version: 0.0.7
Summary: simple sum
Home-page: https://github.com/saninstein/test
Author: Alex Bibik
Author-email: saninstein@gmail.com
License: UNKNOWN
Platform: UNKNOWN
Classifier: Programming Language :: Python :: 3
Classifier: License :: OSI Approved :: MIT License
Classifier: Operating System :: OS Independent
Requires-Python: >=3.6
Provides-Extra: dev
Requires-Dist: pytest ; extra == 'dev'
Requires-Dist: pytest-cov ; extra == 'dev'
Requires-Dist: flake8 ; extra == 'dev'
